Metadata-Version: 2.1
Name: loguru
Version: 0.7.1
Summary: Python logging made (stupidly) simple
Home-page: https://github.com/Delgan/loguru
Download-URL: https://github.com/Delgan/loguru/archive/0.7.1.tar.gz
Author: Delgan
Author-email: delgan.py@gmail.com
License: MIT license
Project-URL: Changelog, https://github.com/Delgan/loguru/blob/master/CHANGELOG.rst
Project-URL: Documentation, https://loguru.readthedocs.io/en/stable/index.html
Keywords: loguru,logging,logger,log
Classifier: Development Status :: 5 - Production/Stable
Classifier: Topic :: System :: Logging
Classifier: Intended Audience :: Developers
Classifier: Natural Language :: English
Classifier: License :: OSI Approved :: MIT License
Classifier: Operating System :: OS Independent
Classifier: Programming Language :: Python
Classifier: Programming Language :: Python :: 3
Classifier: Programming Language :: Python :: 3.5
Classifier: Programming Language :: Python :: 3.6
Classifier: Programming Language :: Python :: 3.7
Classifier: Programming Language :: Python :: 3.8
Classifier: Programming Language :: Python :: 3.9
Classifier: Programming Language :: Python :: 3.10
Classifier: Programming Language :: Python :: 3.11
Classifier: Programming Language :: Python :: 3 :: Only
Classifier: Programming Language :: Python :: Implementation :: PyPy
Classifier: Programming Language :: Python :: Implementation :: CPython
Requires-Python: >=3.5
Provides-Extra: dev
License-File: LICENSE
